MANIFEST.in
Makefile
README
setup.py
test/__init__.py
test/__init__.pyc
test/setup_test.py
test/test.bmp
test/test_post_binary.py
test/test_post_error.py
test/test_post_text.py
test/test_redirect.py
test/test_urls.py
test/__pycache__/setup_test.cpython-27-PYTEST.pyc
test/__pycache__/test_post_binary.cpython-27-PYTEST.pyc
test/__pycache__/test_post_error.cpython-27-PYTEST.pyc
test/__pycache__/test_post_text.cpython-27-PYTEST.pyc
test/__pycache__/test_redirect.cpython-27-PYTEST.pyc
test/__pycache__/test_urls.cpython-27-PYTEST.pyc
tiddlywebplugins/__init__.py
tiddlywebplugins/form.py
tiddlywebplugins.form.egg-info/PKG-INFO
tiddlywebplugins.form.egg-info/SOURCES.txt
tiddlywebplugins.form.egg-info/dependency_links.txt
tiddlywebplugins.form.egg-info/namespace_packages.txt
tiddlywebplugins.form.egg-info/not-zip-safe
tiddlywebplugins.form.egg-info/requires.txt
tiddlywebplugins.form.egg-info/top_level.txt