Metadata-Version: 1.0
Name: tiddlywebplugins.form
Version: 0.11
Summary: Adds POST and binary file upload (via HTML) support to TiddlyWeb
Home-page: http://pypi.python.org/pypi/tiddlywebplugins.form
Author: Ben Gillies
Author-email: bengillies@gmail.com
License: UNKNOWN
Platform: Posix; MacOS X; Windows
